vasudev/__init__.py
vasudev/vasudev.py
vasudev-0.1.0.dist-info/METADATA
vasudev-0.1.0.dist-info/WHEEL
vasudev-0.1.0.dist-info/entry_points.txt
vasudev-0.1.0.dist-info/top_level.txt
vasudev-0.1.0.dist-info/RECORD
