Metadata-Version: 2.4
Name: vasudev
Version: 0.1.0
Summary: Exclusive development toolkit for projects and services by Ankit Chaubey (aka Vasu).
Home-page: https://github.com/ankit-chaubey/vasudev
Author: Ankit Chaubey
Author-email: m.ankitchaubey@gmail.com
Project-URL: Source, https://github.com/ankit-chaubey/vasudev
Project-URL: Bug Tracker, https://github.com/ankit-chaubey/vasudev/issues
Keywords: development automation project-configuration exclusive
Classifier: Development Status :: 4 - Beta
Classifier: Intended Audience :: Developers
Classifier: Topic :: Software Development :: Build Tools
Classifier: Programming Language :: Python :: 3
Classifier: License :: OSI Approved :: MIT License
Classifier: Operating System :: OS Independent
Requires-Python: >=3.6
Requires-Dist: colorama
Dynamic: author
Dynamic: author-email
Dynamic: classifier
Dynamic: description
Dynamic: description-content-type
Dynamic: home-page
Dynamic: keywords
Dynamic: project-url
Dynamic: requires-dist
Dynamic: requires-python
Dynamic: summary
